odoo/addons/mrp_auto_create_lot/README.rst
odoo/addons/mrp_auto_create_lot/__init__.py
odoo/addons/mrp_auto_create_lot/__manifest__.py
odoo/addons/mrp_auto_create_lot/i18n/mrp_auto_create_lot.pot
odoo/addons/mrp_auto_create_lot/models/__init__.py
odoo/addons/mrp_auto_create_lot/models/mrp_workorder.py
odoo/addons/mrp_auto_create_lot/readme/CONTRIBUTORS.rst
odoo/addons/mrp_auto_create_lot/readme/DESCRIPTION.rst
odoo/addons/mrp_auto_create_lot/readme/HISTORY.rst
odoo/addons/mrp_auto_create_lot/readme/USAGE.rst
odoo/addons/mrp_auto_create_lot/static/description/icon.png
odoo/addons/mrp_auto_create_lot/static/description/index.html
odoo/addons/mrp_auto_create_lot/tests/__init__.py
odoo/addons/mrp_auto_create_lot/tests/test_auto_create_lot.py
odoo12_addon_mrp_auto_create_lot-12.0.1.0.1.dist-info/METADATA
odoo12_addon_mrp_auto_create_lot-12.0.1.0.1.dist-info/WHEEL
odoo12_addon_mrp_auto_create_lot-12.0.1.0.1.dist-info/top_level.txt
odoo12_addon_mrp_auto_create_lot-12.0.1.0.1.dist-info/RECORD
