Metadata-Version: 2.1
Name: odoo12-addon-mrp-auto-create-lot
Version: 12.0.1.0.1
Summary: Auto create lots for work orders
Home-page: https://github.com/OCA/manufacture
Author: Ecosoft, Odoo Community Association (OCA)
Author-email: support@odoo-community.org
License: AGPL-3
Platform: UNKNOWN
Classifier: Programming Language :: Python
Classifier: Framework :: Odoo
Classifier: License :: OSI Approved :: GNU Affero General Public License v3
Requires-Python: >=3.5
Requires-Dist: odoo12-addon-stock-picking-auto-create-lot
Requires-Dist: odoo (<12.1dev,>=12.0a)
